async_googlemaps/__init__.py
async_googlemaps/async_client.py
async_googlemaps/convert.py
async_googlemaps/directions.py
async_googlemaps/distance_matrix.py
async_googlemaps/elevation.py
async_googlemaps/exceptions.py
async_googlemaps/geocoding.py
async_googlemaps/geolocation.py
async_googlemaps/maps.py
async_googlemaps/places.py
async_googlemaps/roads.py
async_googlemaps/timezone.py
async_googlemaps-0.0.10.dist-info/METADATA
async_googlemaps-0.0.10.dist-info/WHEEL
async_googlemaps-0.0.10.dist-info/top_level.txt
async_googlemaps-0.0.10.dist-info/RECORD
