Metadata-Version: 2.1
Name: async_googlemaps
Version: 0.0.10
Summary: Asynchronous Python client library for Google Maps Platform
Home-page: https://github.com/shane806/async_googlemaps
License: Apache 2.0
Platform: Posix; MacOS X; Windows
Classifier: Intended Audience :: Developers
Classifier: License :: OSI Approved :: Apache Software License
Classifier: Operating System :: OS Independent
Classifier: Programming Language :: Python :: 3.5
Classifier: Programming Language :: Python :: 3.6
Classifier: Programming Language :: Python :: 3.7
Classifier: Programming Language :: Python :: 3.8
Classifier: Topic :: Internet
Requires-Python: >=3.5
